Compiled from "Math.java"
public class com.study.jvm.classloader.Math {
  public static int initData;

  public static com.study.jvm.classloader.User user;

  public com.study.jvm.classloader.Math();
    Code:
       0: aload_0
       1: invokespecial #1                  // Method java/lang/Object."<init>":()V
       4: return

  public int compute();
    Code:
       0: iconst_1
       1: istore_1
       2: iconst_2
       3: istore_2
       4: iload_1
       5: iload_2
       6: iadd
       7: bipush        10
       9: imul
      10: istore_3
      11: iload_3
      12: ireturn

  public static void main(java.lang.String[]);
    Code:
       0: new           #2                  // class com/study/jvm/classloader/Math
       3: dup
       4: invokespecial #3                  // Method "<init>":()V
       7: astore_1
       8: aload_1
       9: invokevirtual #4                  // Method compute:()I
      12: istore_2
      13: getstatic     #5                  // Field java/lang/System.out:Ljava/io/PrintStream;
      16: new           #6                  // class java/lang/StringBuilder
      19: dup
      20: invokespecial #7                  // Method java/lang/StringBuilder."<init>":()V
      23: ldc           #8                  // String compute value is
      25: invokevirtual #9                  // Method java/lang/StringBuilder.append:(Ljava/lang/String;)Ljava/lang/StringBuilder;
      28: iload_2
      29: invokevirtual #10                 // Method java/lang/StringBuilder.append:(I)Ljava/lang/StringBuilder;
      32: invokevirtual #11                 // Method java/lang/StringBuilder.toString:()Ljava/lang/String;
      35: invokevirtual #12                 // Method java/io/PrintStream.println:(Ljava/lang/String;)V
      38: getstatic     #13                 // Field user:Lcom/study/jvm/classloader/User;
      41: ldc           #14                 // String zhangsan
      43: invokevirtual #15                 // Method com/study/jvm/classloader/User.setName:(Ljava/lang/String;)V
      46: getstatic     #13                 // Field user:Lcom/study/jvm/classloader/User;
      49: bipush        18
      51: invokestatic  #16                 // Method java/lang/Integer.valueOf:(I)Ljava/lang/Integer;
      54: invokevirtual #17                 // Method com/study/jvm/classloader/User.setAge:(Ljava/lang/Integer;)V
      57: getstatic     #13                 // Field user:Lcom/study/jvm/classloader/User;
      60: invokevirtual #18                 // Method com/study/jvm/classloader/User.output:()V
      63: getstatic     #5                  // Field java/lang/System.out:Ljava/io/PrintStream;
      66: ldc           #19                 // String User test end
      68: invokevirtual #12                 // Method java/io/PrintStream.println:(Ljava/lang/String;)V
      71: return

  static {};
    Code:
       0: sipush        666
       3: putstatic     #20                 // Field initData:I
       6: new           #21                 // class com/study/jvm/classloader/User
       9: dup
      10: invokespecial #22                 // Method com/study/jvm/classloader/User."<init>":()V
      13: putstatic     #13                 // Field user:Lcom/study/jvm/classloader/User;
      16: return
}
